<?xml version="1.0" encoding="UTF-8"?>
<!DOCTYPE filesystem PUBLIC "-//NetBeans//DTD Filesystem 1.2//EN" "http://www.netbeans.org/dtds/filesystem-1_2.dtd">
<filesystem>
    <attr name="Menu\File\Import\position" intvalue="1600"/>
    <attr name="Menu\File\Export\position" intvalue="1650"/>
    <attr name="Menu\File\ImporterSeparator1.instance\position" intvalue="1700"/>
    <attr name="Menu\File\Separator2.instance\position" intvalue="1500"/>
    <attr name="Menu\File\Separator3.instance\position" intvalue="2300"/>
    <attr name="Menu\File\Separator4.instance\position" intvalue="2700"/>
    <attr name="Menu\File\SeparatorNew.instance\position" intvalue="500"/>
    <attr name="Menu\File\SeparatorOpen.instance\position" intvalue="1200"/>
    <attr name="Menu\File\org-netbeans-core-actions-SystemExit.instance\position" intvalue="2800"/>
    <attr name="Menu\File\org-netbeans-modules-editor-ExportHtmlAction.instance\position" intvalue="2600"/>
    <attr name="Menu\File\org-netbeans-modules-openfile-OpenFileAction.shadow\position" intvalue="1000"/>
    <attr name="Menu\File\org-netbeans-modules-openfile-RecentFileAction.instance\position" intvalue="1100"/>
    <attr name="Menu\File\org-netbeans-modules-print-action-PageSetupAction.shadow\position" intvalue="2400"/>
    <attr name="Menu\File\org-netbeans-modules-project-ui-CloseProject.shadow\position" intvalue="900"/>
    <attr name="Menu\File\org-netbeans-modules-project-ui-CustomizeProject.shadow\position" intvalue="1400"/>
    <attr name="Menu\File\org-netbeans-modules-project-ui-NewFile.shadow\position" intvalue="400"/>
    <attr name="Menu\File\org-netbeans-modules-project-ui-NewProject.shadow\position" intvalue="300"/>
    <attr name="Menu\File\org-netbeans-modules-project-ui-OpenProject.shadow\position" intvalue="600"/>
    <attr name="Menu\File\org-netbeans-modules-project-ui-RecentProjects.shadow\position" intvalue="700"/>
    <attr name="Menu\File\org-netbeans-modules-project-ui-groups-GroupsMenu.shadow\position" intvalue="1300"/>
    <attr name="Menu\File\org-openide-actions-SaveAction.instance\position" intvalue="1850"/>
    <attr name="Menu\File\org-openide-actions-SaveAllAction.instance\position" intvalue="2200"/>
    <attr name="Menu\File\org-openide-actions-SaveAsAction.instance\position" intvalue="2100"/>
    <folder name="Actions">
        <folder name="Edit">
            <file name="ancestris-app-ActionHistory.instance">
                <attr name="iconBase" stringvalue="ancestris/view/images/Forward.png"/>
                <attr name="SystemFileSystem.localizingBundle" stringvalue="ancestris.app.Bundle"/>
                <attr name="displayName" bundlevalue="ancestris.app.Bundle#CTL_ActionHistory"/>
                <attr name="noIconInMenu" boolvalue="false"/>
            </file>    
            <file name="org-openide-actions-GotoAction.instance_hidden"/>
            <file name="org-openide-actions-DeleteAction.instance_hidden"/>
            <file name="org-openide-actions-CopyAction.instance">
                <attr name="instanceCreate" methodvalue="org.openide.awt.Actions.callback"/>
                <attr name="key" stringvalue="copy-to-clipboard"/>
                <attr name="iconBase" stringvalue="org/openide/resources/actions/copy.gif"/>
                <attr name="displayName" bundlevalue="org.openide.actions.Bundle#Copy"/>
            </file>
            <file name="org-openide-actions-CutAction.instance">
                <attr name="instanceCreate" methodvalue="org.openide.awt.Actions.callback"/>
                <attr name="key" stringvalue="cut-to-clipboard"/>
                <attr name="iconBase" stringvalue="org/openide/resources/actions/cut.gif"/>
                <attr name="displayName" bundlevalue="org.openide.actions.Bundle#Cut"/>
            </file>
            <file name="org-openide-actions-PasteAction.instance">
                <attr name="instanceCreate" methodvalue="org.openide.awt.Actions.callback"/>
                <attr name="key" stringvalue="paste-from-clipboard"/>
                <attr name="iconBase" stringvalue="org/openide/resources/actions/paste.gif"/>
                <attr name="displayName" bundlevalue="org.openide.actions.Bundle#Paste"/>
            </file>
            <file name="org-netbeans-modules-quicksearch-QuickSearchAction.instance">
                <attr name="iconBase" stringvalue="ancestris/view/images/Find.png"/>  
            </file>
            <file name="org-openide-actions-FindAction.instance">
                <attr name="SystemFileSystem.localizingBundle" stringvalue="ancestris.app.Bundle"/>
                <attr name="delegate" newvalue="ancestris.app.ActionFind"/>
                <attr name="iconBase" stringvalue="ancestris/view/images/Find.png"/>  
                <attr name="displayName" bundlevalue="ancestris.app.Bundle#CTL_ActionFind"/>
                <attr name="instanceCreate" methodvalue="org.openide.awt.Actions.alwaysEnabled"/>
                <attr name="noIconInMenu" boolvalue="false"/>
            </file>
            <file name="org-openide-actions-ReplaceAction.instance">
                <attr name="SystemFileSystem.localizingBundle" stringvalue="ancestris.app.Bundle"/>
                <attr name="delegate" newvalue="ancestris.app.ActionReplace"/>
                <attr name="displayName" bundlevalue="ancestris.app.Bundle#CTL_ActionReplace"/>
                <attr name="iconBase" stringvalue="ancestris/view/images/Replace.png"/>
                <attr name="instanceCreate" methodvalue="org.openide.awt.Actions.alwaysEnabled"/>
                <attr name="noIconInMenu" boolvalue="false"/>
            </file>
        </folder>
        <folder name="File">
            <file name="ancestris-app-ActionNew.instance">
                <attr name="SystemFileSystem.localizingBundle" stringvalue="ancestris.app.Bundle"/>
                <attr name="delegate" newvalue="ancestris.app.ActionNew"/>
                <attr name="displayName" bundlevalue="ancestris.app.Bundle#CTL_ActionNew"/>
                <attr name="iconBase" stringvalue="ancestris/view/images/New.png"/>
                <attr name="instanceCreate" methodvalue="org.openide.awt.Actions.alwaysEnabled"/>
                <attr name="noIconInMenu" boolvalue="false"/>
            </file>
            <file name="ancestris-app-ActionOpenDefault.instance">
                <attr name="type" stringvalue="org.netbeans.api.actions.Openable"/>
                <attr name="delegate" methodvalue="org.openide.awt.Action.inject"/>
                <attr name="selectionType" stringvalue="ANY"/>
                <attr name="injectable" stringvalue="ancestris.app.ActionOpenDefault"/>
                <attr name="displayName" bundlevalue="ancestris.app.Bundle#CTL_ActionOpenDefault"/>
                <attr name="iconBase" stringvalue="ancestris/view/images/OpenDefault.png"/>
            </file>
            <file name="ancestris-app-ActionOpen.instance">
                <attr name="SystemFileSystem.localizingBundle" stringvalue="ancestris.app.Bundle"/>
                <attr name="delegate" newvalue="ancestris.app.ActionOpen"/>
                <attr name="displayName" bundlevalue="ancestris.app.Bundle#CTL_ActionOpen"/>
                <attr name="iconBase" stringvalue="ancestris/view/images/Open.png"/>
                <attr name="instanceCreate" methodvalue="org.openide.awt.Actions.alwaysEnabled"/>
                <attr name="noIconInMenu" boolvalue="false"/>
            </file>
            <file name="ancestris-app-ActionClose.instance">
                <attr name="SystemFileSystem.localizingBundle" stringvalue="ancestris.app.Bundle"/>
                <attr name="delegate" newvalue="ancestris.app.ActionClose"/>
                <attr name="displayName" bundlevalue="ancestris.app.Bundle#CTL_ActionClose"/>
                <attr name="iconBase" stringvalue="ancestris/view/images/Close.png"/>
                <attr name="instanceCreate" methodvalue="org.openide.awt.Actions.alwaysEnabled"/>
                <attr name="noIconInMenu" boolvalue="false"/>
            </file>
             <!--<file name="ancestris-app-ActionSave.instance">
                <attr name="delegate" newvalue="ancestris.app.ActionSave"/>
                <attr name="iconBase" stringvalue="ancestris/view/images/Save.png"/>
            </file>-->
            <file name="ancestris-app-ActionSaveAs.instance">
                <attr name="delegate" newvalue="ancestris.app.ActionSaveAs"/>
            </file>
            <file name="org-netbeans-modules-print-action-PrintAction.instance">
                <attr name="SystemFileSystem.localizingBundle" stringvalue="org.netbeans.modules.print.resources.Bundle"/>
                <attr name="delegate" newvalue="org.netbeans.modules.print.action.PrintAction"/>
                <attr name="displayName" bundlevalue="org.netbeans.modules.print.action.Bundle#TLT_Print_Action"/>
                <attr name="iconBase" stringvalue="ancestris/view/images/Print.png"/>
                <attr name="instanceCreate" methodvalue="org.openide.awt.Actions.alwaysEnabled"/>
                <attr name="noIconInMenu" boolvalue="false"/>
            </file>
        </folder>
        <folder name="Tools">
            <file name="MyOptions.instance">
                <attr name="SystemFileSystem.localizingBundle" stringvalue="ancestris.app.Bundle"/>
                <attr name="delegate" newvalue="org.netbeans.modules.options.OptionsWindowAction"/>  <!-- the name of the options menuitem (FL) -->
                <attr name="displayName" bundlevalue="ancestris.app.Bundle#OptionsCategory_Title_AncestrisPreference"/>
                <attr name="iconBase" stringvalue="ancestris/view/images/Options.png"/>
                <attr name="instanceCreate" methodvalue="org.openide.awt.Actions.alwaysEnabled"/>
                <attr name="noIconInMenu" boolvalue="false"/>
            </file>
        </folder>
        <folder name="Window">
            <file name="ancestris-app-SaveLayoutAction.instance">
                <attr name="SystemFileSystem.localizingBundle" stringvalue="ancestris.app.Bundle"/>
                <attr name="instanceCreate" methodvalue="org.openide.awt.Actions.alwaysEnabled"/>
                <attr name="delegate" newvalue="ancestris.app.ActionSaveLayout"/>
                <attr name="displayName" bundlevalue="ancestris.app.Bundle#CTL_SaveLayout"/>
                <attr name="iconBase" stringvalue="ancestris/view/images/SaveLayout.png"/>
                <attr name="noIconInMenu" boolvalue="false"/>
            </file>
            <file name="ancestris-explorer-GedcomExplorerAction.instance">
                <attr name="component" methodvalue="ancestris.explorer.GedcomExplorerTopComponent.findInstance"/>
                <attr name="displayName" bundlevalue="ancestris.explorer.Bundle#CTL_GedcomExplorerAction"/>
                <attr name="instanceCreate" methodvalue="org.openide.windows.TopComponent.openAction"/>
                <attr name="iconBase" stringvalue="ancestris/explorer/explorer.png"/>
            </file>
            <file name="org-netbeans-core-windows-actions-ResetWindowsAction.instance_hidden"/>
        </folder>
        <folder name="Help">
            <!-- Override the registered action with the new one. This will be
                 used by code that calls SystemAction.get(...), e.g. the AppleMenu module -->
            <file name="ancestris-app-ActionOnlineHelp.instance">
                <attr name="SystemFileSystem.localizingBundle" stringvalue="ancestris.app.Bundle"/>
                <attr name="delegate" newvalue="ancestris.app.ActionOnlineHelp"/>
                <attr name="displayName" bundlevalue="ancestris.app.Bundle#CTL_ActionOnlineHelp"/>
                <attr name="iconBase" stringvalue="ancestris/view/images/Help.png"/>
                <attr name="instanceCreate" methodvalue="org.openide.awt.Actions.alwaysEnabled"/>
                <attr name="noIconInMenu" boolvalue="false"/>
            </file>
            <file name="ancestris-app-ActionAncestrisSite.instance">
                <attr name="delegate" newvalue="ancestris.app.ActionAncestrisSite"/>
                <attr name="iconBase" stringvalue="ancestris/view/images/AncestrisSite.png"/>
            </file>
            <file name="ancestris-app-ActionAPropos.instance">
                <attr name="delegate" newvalue="ancestris.app.ActionAPropos"/>
                <attr name="displayName" bundlevalue="ancestris.app.Bundle#CTL_ActionAPropos"/>
                <attr name="iconBase" stringvalue="ancestris/view/images/About.png"/>
                <attr name="instanceCreate" methodvalue="org.openide.awt.Actions.alwaysEnabled"/>
                <attr name="noIconInMenu" boolvalue="false"/>
            </file>
        </folder>
        <folder name="System">
            <file name="org-openide-actions-SaveAction.instance">
                <attr name="iconBase" stringvalue="ancestris/view/images/Save.png"/>
                <attr name="noIconInMenu" boolvalue="false"/>
            </file>
            <file name="org-netbeans-modules-autoupdate-ui-actions-PluginManagerAction.instance">
                <attr name="displayName" bundlevalue="ancestris.app.Bundle#CTL_InstallPlugins"/>
                <attr name="iconBase" stringvalue="ancestris/view/images/Extension.png"/>
                <attr name="noIconInMenu" boolvalue="false"/>
            </file>
            <file name="org-netbeans-modules-autoupdate-ui-actions-CheckForUpdatesAction.instance">
                <attr name="iconBase" stringvalue="org/netbeans/modules/autoupdate/ui/resources/newUpdates.png"/>
                <attr name="noIconInMenu" boolvalue="false"/>
            </file>
        </folder>
    </folder>
    <file name="BugtrackingOptionsDialog_hidden"/>
    <file name="DTDs_hidden"/>
    <file name="Databases_hidden"/>
    <file name="Debugger_hidden"/>
    <file name="FormDesignerPalette_hidden"/>
    <file name="HTTPServer_DUMMY_hidden"/>
    <file name="Maven2Templates_hidden"/>
    
    
    <!-- ===============================================================================-->
    <!--                            THIS IS ANCESTRIS MAIN MENU                         -->
    <!-- ===============================================================================-->
    <folder name="Menu">
        <folder name="File"> <!-- ===================================================  FICHIER =================================================== -->
            <attr name="position" intvalue="100"/>
            <!-- ======  Créer une généalogie ======-->
            <file name="ancestris-app-ActionNew.shadow">  
                <attr name="originalFile" stringvalue="Actions/File/ancestris-app-ActionNew.instance"/>
                <attr name="position" intvalue="100"/>
            </file>
            <!-- ======  Ouvrir généalogie par défaut  ======-->
            <file name="ancestris-app-ActionOpenDefault.shadow">  
                <attr name="originalFile" stringvalue="Actions/File/ancestris-app-ActionOpenDefault.instance"/>
                <attr name="position" intvalue="150"/>
            </file>
            <!-- ======  Ouvrir une généalogie ======-->
            <file name="ancestris-app-ActionOpen.shadow"> 
                <attr name="originalFile" stringvalue="Actions/File/ancestris-app-ActionOpen.instance"/>
                <attr name="position" intvalue="200"/>
            </file>
            <!-- ======  Importer ===250===-->
            <folder name="Import">
                <attr name="position" intvalue="250"/>
                <attr name="displayName" bundlevalue="ancestris.app.Bundle#Menu/File/Import"/> 
            </folder>
            <!-- ======  Réunir =====300=-->
            <!-- =========================-->
            <file name="Separator2.instance">
                <attr name="position" intvalue="350"/>
            </file>
            <!-- ======  Propriétés ==400====-->
            <!-- ======  Ajouter aux favoris = (we need to add the instance itself, not just the shadow)=====-->
            <file name="org-netbeans-modules-favorites-Add.shadow">
                <attr name="originalFile" stringvalue="Actions/Window/org-netbeans-modules-favorites-Add.instance"/>
                <attr name="position" intvalue="451"/>
            </file>
            <!-- =========================-->
            <file name="Separator3.instance">
                <attr name="position" intvalue="500"/>
            </file>
            <!-- ======  Enregistrer ======-->
            <file name="org-openide-actions-SaveAction.shadow">  
                <attr name="originalFile" stringvalue="Actions/System/org-openide-actions-SaveAction.instance"/>
                <attr name="position" intvalue="530"/>
            </file>
            <!-- ======  Enregistrer Sous... ======-->
            <file name="ancestris-app-ActionSaveAs.shadow"> 
                <attr name="originalFile" stringvalue="Actions/File/ancestris-app-ActionSaveAs.instance"/>
                <attr name="position" intvalue="550"/>
            </file>
            <!-- ======  Exporter ==600====-->
            <folder name="Export">
                <attr name="position" intvalue="600"/>
                <attr name="displayName" bundlevalue="ancestris.app.Bundle#Menu/File/Export"/> 
            </folder>
            <!-- =========================-->
            <file name="Separator4.instance">
                <attr name="position" intvalue="700"/>
            </file>
            <!-- ======  Fermer ======-->
            <file name="ancestris-app-ActionClose.shadow"> 
                <attr name="originalFile" stringvalue="Actions/File/ancestris-app-ActionClose.instance"/>
                <attr name="position" intvalue="2500"/>
            </file>
            <!-- ======  Quitter ======-->
            <file name="org-netbeans-core-actions-SystemExit.shadow">
                <attr name="position" intvalue="2600"/>
            </file>
            <!-- hidden -->
            <!--<file name="ancestris-app-ActionSave.shadow">
                <attr name="originalFile" stringvalue="Actions/File/ancestris-app-ActionSave.instance"/>
                <attr name="position" intvalue="1801"/>
                <attr name="noIconInMenu" boolvalue="true"/>
            </file>-->
            <file name="org-openide-actions-SaveAsAction.shadow_hidden">
                <attr name="position" intvalue="9000"/>
            </file>
            <file name="org-openide-actions-SaveAllAction.shadow_hidden">
                <attr name="position" intvalue="9010"/>
            </file>
            <file name="org-openide-actions-PageSetupAction.shadow_hidden">
                <attr name="position" intvalue="9025"/>
            </file>
            <file name="org-netbeans-modules-print-action-PageSetupAction.shadow_hidden">
                <attr name="position" intvalue="9030"/>
            </file>
            <file name="org-openide-actions-PrintAction.shadow_hidden">
                <attr name="position" intvalue="9035"/>
            </file>
            <file name="org-netbeans-modules-print-action-PrintAction.shadow_hidden">
                <attr name="position" intvalue="9040"/>
            </file>
        </folder>
        
        
        <folder name="Edit"> <!-- ===================================================  EDITION =================================================== -->
            <attr name="displayName" bundlevalue="ancestris.app.Bundle#Menu/Edit"/>
            <attr name="position" intvalue="200"/>
            <!-- ======  Annuler ======-->
            <!-- ======  Rétablir ======-->
            <!-- =========================-->
            <!-- ======  Couper ======-->
            <!-- ======  Copier ======-->
            <!-- ======  Coller ======-->
            <!-- =========================-->
            <!-- ======  Rechercher ======-->
            <!-- ======  Remplacer ==2100====-->
            <!-- ======  Supprimer ==2200====-->
            <!-- =========================-->
            <file name="Separator3.instance">
                <attr name="instanceClass" stringvalue="javax.swing.JSeparator"/>
                <attr name="position" intvalue="2300"/>
            </file>
            <!-- ======  Numéroter Sosa ==2400====-->
            <!-- ======  Mémoriser modifications =2500=====-->
            
            <!-- hidden -->
            <file name="org-netbeans-modules-search-FindInFilesAction-separatorBefore.instance_hidden">
                <attr name="position" intvalue="9000"/>
            </file>
            <file name="org-openide-actions-DeleteAction.shadow_hidden">
                <attr name="position" intvalue="9005"/>
            </file>
            <file name="org-netbeans-modules-search-FindInFilesAction.shadow_hidden">
                <attr name="position" intvalue="9010"/>
            </file>
            <file name="org-netbeans-modules-search-ReplaceInFilesAction.shadow_hidden">
                <attr name="position" intvalue="9020"/>
            </file>
        </folder>
        
        
        <folder name="View"> <!-- ===================================================  VUE =================================================== -->
            <attr name="position" intvalue="300"/>
            <!-- ======  Fiche entité ======-->
            <!-- =========================-->
            <file name="Separator1.instance">
                <attr name="instanceClass" stringvalue="javax.swing.JSeparator"/>
                <attr name="position" intvalue="-990"/>
            </file>
            <!-- ======  Table ======-->
            <!-- ======  Arbre ======-->
            <!-- ======  Chrono ======-->
            <!-- ======  Carte Geo ======-->
            <!-- ======  Graphe ======-->
            <!-- =========================-->
            <file name="Separator1_1_2.instance">
                <attr name="instanceClass" stringvalue="javax.swing.JSeparator"/>
                <attr name="position" intvalue="-600"/>
            </file>
            <!-- ======  Cygnus ======-->
            <!-- ======  Editeur Gedcom ======-->
            <file name="EditAction.shadow">
                <attr name="originalFile" stringvalue="Actions/Window/ancestris-app-EditAction.instance"/>
                <attr name="position" intvalue="-500"/>
            </file>
            <!-- ======  Aries ======-->
            <!-- =========================-->
            <file name="Separator1_1_1.instance">
                <attr name="instanceClass" stringvalue="javax.swing.JSeparator"/>
                <attr name="position" intvalue="-450"/>
            </file>
            <!-- ======  Liste lieux ======-->
            <!-- ======  Table lieux ======-->
            <!-- =========================-->
            <file name="Separator1_1_3.instance">
                <attr name="instanceClass" stringvalue="javax.swing.JSeparator"/>
                <attr name="position" intvalue="-400"/>
            </file>
            <!-- ======  Navigateur simple ======-->
            <!-- ======  Navigateur étendu ======-->
            <!-- ======  Recherche avancée ======-->
            <file name="SearchAction.shadow">
                <attr name="originalFile" stringvalue="Actions/Window/ancestris-app-SearchAction.instance"/>
                <attr name="position" intvalue="-250"/>
            </file>
             <!-- hidden -->
            <file name="Separator2.instance_hidden">
                <attr name="position" intvalue="9000"/>
            </file>
            <file name="Separator3.instance_hidden">
                <attr name="position" intvalue="9010"/>
            </file>
            <file name="org-netbeans-core-windows-actions-ToolbarsListAction.shadow_hidden">
                <attr name="position" intvalue="9020"/>
            </file>
            <file name="ShowEditorOnlyAction.shadow_hidden">
                <attr name="position" intvalue="9030"/>
            </file>
            <file name="ToggleFullScreenAction.shadow_hidden">
                <attr name="position" intvalue="9040"/>
            </file>
            <file name="org-netbeans-core-multiview-EditorsAction.instance_hidden"/>
            <file name="org-netbeans-core-multiview-SplitAction.instance_hidden"/>
            <file name="org-netbeans-core-actions-HTMLViewAction.shadow_hidden"/>
            <file name="org-netbeans-core-actions-LogAction.shadow_hidden"/>
        </folder>
        
        
        <folder name="Tools"><!-- ===================================================  OUTILS =================================================== -->
            <attr name="position" intvalue="400"/>
            <!-- ======  Recherche généalogique ===10===-->
            <!-- ======  Relevé ===30===-->
            <!-- ======  Datulette ===35===-->
            <!-- ======  Calculette ==40====-->
            <!-- ====================50=====-->
            <file name="Separator1.instance">
                <attr name="position" intvalue="99"/>
            </file>
            <!-- ======  Vérification norme Gedcom ==60====-->
            <!-- ======  Fusion de doublon ===80===-->
            <!-- ===================99======-->
            <file name="Separator2.instance">
                <attr name="instanceClass" stringvalue="javax.swing.JSeparator"/>
                <attr name="position" intvalue="50"/>
            </file>
            <!-- ======  Ancêtres communs ==100====-->
            <!-- ======  Rapport Direct (liste éclair, groupe familiaux, parents proches) ==120====-->
            <folder name="Reports">
                <attr name="displayName" bundlevalue="ancestris.app.Bundle#Menu/Tools/Reports"/>
                <attr name="position" intvalue="120"/>
            </folder>
            <!-- ======  Liste et rapports =140=====-->
            <!-- ======  Publication (livre web, site web) ==160====-->
            <folder name="Multimedia">
                <attr name="displayName" bundlevalue="ancestris.app.Bundle#Menu/Tools/Multimedia"/>
                <attr name="iconBase" stringvalue="ancestris/view/images/Publication.png"/>
                <attr name="position" intvalue="160"/>
            </folder>
            <!-- ======  Impression de la vue active ======-->
            <file name="org-netbeans-modules-print-action-PrintAction.shadow"> 
                <attr name="originalFile" stringvalue="Actions/File/org-netbeans-modules-print-action-PrintAction.instance"/>
                <attr name="position" intvalue="2200"/>
            </file>
            <!-- hidden -->
            <file name="org-netbeans-modules-apisupport-project-ui-platform-NbPlatformCustomizerAction.instance_hidden">
                <attr name="position" intvalue="9000"/>
            </file>
            <file name="org-netbeans-modules-options-OptionsWindowAction.shadow_hidden">   <!-- the tag of the options menuitem (FL) -->
                <attr name="position" intvalue="9010"/>
            </file>
            <file name="org-netbeans-modules-templates-actions-TemplatesAction.shadow_hidden"> <!-- 2016-01-16 - the tag of the Modeles menuitem (FL) -->
                <attr name="position" intvalue="9020"/>
            </file>
            <file name="org-netbeans-modules-xml-catalog-CatalogAction.instance_hidden">
                <attr name="position" intvalue="9030"/>
            </file>
            <file name="org-netbeans-modules-options-OptionsWindowAction-separatorBefore.instance_hidden">
                <attr name="position" intvalue="9040"/>
            </file>
            <file name="org-netbeans-modules-autoupdate-ui-actions-PluginManagerAction.shadow_hidden">
                <attr name="position" intvalue="9050"/>
            </file>
            <file name="JavaPlatformsCustomizerAction.instance_hidden">
                <attr name="position" intvalue="9060"/>
            </file>
            <file name="VariablesCustomizerAction.instance_hidden">
                <attr name="position" intvalue="9070"/>
            </file>
            <file name="LibrariesCustomizerAction.instance_hidden">
                <attr name="position" intvalue="9080"/>
            </file>
            <file name="ServerManagerAction3.instance_hidden">
                <attr name="position" intvalue="9090"/>
            </file>
            <file name="PaletteManager.instance_hidden">
                <attr name="position" intvalue="9100"/>
            </file>
            <file name="org-openide-actions-ToolsAction.shadow_hidden">
                <attr name="position" intvalue="9120"/>
            </file>
        </folder>
        
        
        <folder name="Window"><!-- ===================================================  FENETRE =================================================== -->
            <attr name="position" intvalue="500"/>
            <!-- ======  Page d'accueil ===100===-->
            <!-- ======  Explorateur gedcom ==200====-->
            <file name="GedcomExplorerAction.shadow"> 
                <attr name="originalFile" stringvalue="Actions/Window/ancestris-explorer-GedcomExplorerAction.instance"/>
                <attr name="position" intvalue="200"/>
            </file>
            <!-- ======  Documents ===300===-->
            <!-- ======  Favoris ==400====-->
            <file name="org-netbeans-modules-favorites-View.shadow">
                <attr name="position" intvalue="400"/>
            </file>
            <!-- <file name="org-netbeans-modules-favorites-View.shadow"/> -->
            <!-- ======  Sortie ====500==-->
            <file name="org-netbeans-core-io-ui-IOWindowAction.shadow">
                <attr name="position" intvalue="500"/>
            </file>
            <!-- =========================-->
            <file name="Separator3.instance">
	        <attr name="instanceClass" stringvalue="javax.swing.JSeparator"/>
	        <attr name="position" intvalue="1000"/>
            </file>
            <!-- ======  Configurer la fenêtre ======-->
            <!-- ======  Fermer ======-->
            <!-- ======  Fermer toutes ======-->
            <!-- ======  Toutes les fenêtres... ======-->
            <!-- =========================-->
            <file name="Separator7.instance">
	        <attr name="instanceClass" stringvalue="javax.swing.JSeparator"/>
	        <attr name="position" intvalue="30000"/>
            </file>
            <!-- ======  Plein écran Fenêtre ======-->
            <file name="ShowEditorOnlyAction.shadow">
                <attr name="originalFile" stringvalue="Actions/Window/org-netbeans-core-windows-actions-ShowEditorOnlyAction.instance"/>
                <attr name="position" intvalue="30100"/>
            </file>
            <!-- ======  Plein écran Ancestris ======-->
            <file name="ToggleFullScreenAction.shadow">
                <attr name="originalFile" stringvalue="Actions/Window/org-netbeans-core-windows-actions-ToggleFullScreenAction.instance"/>
                <attr name="position" intvalue="30200"/>
            </file>
            <!-- hidden -->
            <file name="GroupsMenuAction.shadow_hidden">
                <attr name="position" intvalue="90000"/>
            </file>
            <file name="org-netbeans-core-actions-LogAction.shadow_hidden">
                <attr name="position" intvalue="90100"/>
            </file>
            <file name="SwitchToRecentDocumentAction.shadow_hidden">
                <attr name="position" intvalue="90200"/>
            </file>
            <file name="Tools_hidden">
                <attr name="position" intvalue="90300"/>
            </file>
            <file name="Web_hidden">
                <attr name="position" intvalue="90400"/>
            </file>
            <file name="org-netbeans-core-windows-actions-ResetWindowsAction.shadow_hidden">
                <attr name="position" intvalue="90500"/>
            </file>
            <file name="CloseAllButThisAction.shadow_hidden">
                <attr name="position" intvalue="90600"/>
            </file>
            <folder name="ConfigureWindow">         
		<file name="org-netbeans-core-multiview-SplitAction.instance_hidden"/>
            </folder>
        </folder>
        <folder name="Customization"><!-- ====================================  PERSONNALISATION =================================================== -->
            <attr name="displayName" bundlevalue="ancestris.app.Bundle#Menu/Customization"/>
            <attr name="position" intvalue="600"/>
            <!-- ======  Préférences ======-->
            <file name="MyOptions.shadow">
                <attr name="originalFile" stringvalue="Actions/Tools/MyOptions.instance"/>
                <attr name="position" intvalue="2000"/>
            </file>
            <!-- ======  Conserver la position des fenêtres ======-->
            <file name="ActionSaveLayout.shadow">
                <attr name="originalFile" stringvalue="Actions/Window/ancestris-app-SaveLayoutAction.instance"/>
                <attr name="position" intvalue="2200"/>
            </file>
            <!-- ======  Barre d'outils ======-->
            <file name="org-netbeans-core-windows-actions-ToolbarsListAction.shadow">
                <attr name="originalFile" stringvalue="Actions/Window/org-netbeans-core-windows-actions-ToolbarsListAction.instance"/>
                <attr name="position" intvalue="2400"/>
            </file>
            <!-- ===================================-->
            <file name="Separator7.instance">
	        <attr name="instanceClass" stringvalue="javax.swing.JSeparator"/>
	        <attr name="position" intvalue="2600"/>
            </file>
            <!-- ======  Mise à jour d'Ancestris ======-->
            <file name="org-netbeans-modules-autoupdate-ui-actions-CheckForUpdatesAction.shadow">
                <attr name="originalFile" stringvalue="Actions/System/org-netbeans-modules-autoupdate-ui-actions-CheckForUpdatesAction.instance"/>
                <attr name="position" intvalue="3000"/>
            </file>
            <!-- ======  Extensions ======-->
            <file name="org-netbeans-modules-autoupdate-ui-actions-PluginManagerAction.shadow">
                <attr name="originalFile" stringvalue="Actions/System/org-netbeans-modules-autoupdate-ui-actions-PluginManagerAction.instance"/>
                <attr name="position" intvalue="3200"/>
            </file>
        </folder>    
        
        
        <folder name="Help"><!-- ===================================================  AIDE =================================================== -->
            <attr name="position" intvalue="700"/>
            <!-- ======  Visite guidée ===90===-->
            <file name="ancestris-tour-TourAction.instance">
                <attr name="SystemFileSystem.localizingBundle" stringvalue="ancestris.tour.Bundle"/>
                <attr name="instanceCreate" methodvalue="org.openide.awt.Actions.alwaysEnabled"/>
                <attr name="delegate" newvalue="ancestris.tour.TourAction"/>
                <attr name="displayName" bundlevalue="ancestris.tour.Bundle#ActionName"/>
                <attr name="iconBase" stringvalue="ancestris/tour/tour.png"/>
                <attr name="noIconInMenu" boolvalue="false"/>
                <attr name="position" intvalue="90"/>
            </file>
            <!-- ======  Toute la documentation ===100===-->
            <file name="ancestris-app-ActionOnlineHelp.shadow">
                <attr name="originalFile" stringvalue="Actions/Help/ancestris-app-ActionOnlineHelp.instance"/>
                <attr name="position" intvalue="100"/>
            </file>
            <!-- ======  Contacter l'équipe support ==200====-->
            <!-- ===================300======-->
            <file name="Separator1.instance">
                <attr name="position" intvalue="300"/>
            </file>
            <!-- ======  Faire un don ==400====-->
            <!-- ===================500======-->
            <file name="Separator1.1.instance">
	        <attr name="instanceClass" stringvalue="javax.swing.JSeparator"/>
	        <attr name="position" intvalue="500"/>
            </file>
            <!-- ======  Site Ancestris ===600===-->
            <file name="ancestris-app-ActionAncestrisSite.shadow">
                <attr name="originalFile" stringvalue="Actions/Help/ancestris-app-ActionAncestrisSite.instance"/>
                <attr name="position" intvalue="600"/>
            </file>
            <!-- ======  A propos ===700===-->
            <file name="ancestris-app-ActionAPropos.shadow">
                <attr name="originalFile" stringvalue="Actions/Help/ancestris-app-ActionAPropos.instance"/>
                <attr name="position" intvalue="700"/>
            </file>
             <!-- hidden -->
            <file name="org-netbeans-core-actions-AboutAction.instance_hidden"/>
            <file name="org-netbeans-core-actions-AboutAction.shadow_hidden"/>
            <file name="org-netbeans-modules-javadoc-search-IndexOverviewAction.shadow_hidden"/>
            <file name="org-netbeans-modules-javadoc-search-SearchDocAction.shadow_hidden"/>
            <file name="master-help.xml_hidden"/>
            <file name="org-netbeans-modules-autoupdate-ui-actions-CheckForUpdatesAction.shadow_hidden">
            </file>
        </folder>
        
        <file name="Profile_hidden"/>
        <file name="Refactoring_hidden"/>
        <file name="RunProject_hidden"/>
        <file name="Source_hidden"/>
        <file name="Versioning_hidden"/>
        <file name="GoTo_hidden"/>
        <file name="BuildProject_hidden"/>
    <!-- =================================================================================-->
    <!--                          THIS ENDS ANCESTRIS MAIN MENU                           -->
    <!-- =================================================================================-->
    </folder>
    
    
    
    <folder name="OptionsDialog">
        <file name="Keymaps.instance">
            <attr methodvalue="org.netbeans.spi.options.OptionsCategory.createCategory" name="instanceCreate"/>
            <attr name="controller" newvalue="org.netbeans.modules.options.keymap.KeymapPanelController"/>
            <attr bundlevalue="org.netbeans.modules.options.keymap.Bundle#CTL_Keymap_Options" name="categoryName"/>
            <attr name="position" intvalue="600"/>
            <attr name="iconBase" stringvalue="org/netbeans/modules/options/keymap/keymap.png"/>
            <attr bundlevalue="org.netbeans.modules.options.keymap.Bundle#KW_KeymapOptions" name="keywords"/>
            <attr name="keywordsCategory" stringvalue="Keymaps"/>
        </file>
        <file name="General.instance">
            <attr methodvalue="org.netbeans.spi.options.OptionsCategory.createCategory" name="instanceCreate"/>
            <attr name="controller" newvalue="org.netbeans.core.ui.options.general.GeneralOptionsPanelController"/>
            <attr bundlevalue="org.netbeans.core.ui.options.general.Bundle#CTL_General_Options" name="categoryName"/>
            <attr name="iconBase" stringvalue="org/netbeans/core/ui/options/general/generalOptions.png"/>
            <attr bundlevalue="org.netbeans.core.ui.options.general.Bundle#KW_General" name="keywords"/>
            <attr name="keywordsCategory" stringvalue="General"/>
            <attr name="position" intvalue="900"/>
        </file>
        <file name="Advanced_hidden"/>
        <file name="Advanced.instance_hidden"/>
        <file name="Appearance.instance_hidden"/>
        <file name="Appearance_hidden"/>
    </folder>
    
    
    <folder name="QuickSearch">
        <file name="Actions"/>
        <folder name="Indis">
            <attr name="SystemFileSystem.localizingBundle" stringvalue="ancestris.app.Bundle"/>
            <attr name="command" stringvalue="i"/>
            <attr name="position" intvalue="0"/>
            <file name="ancestris-app-IndiQuickSearch.instance"/>
        </folder>
        <folder name="Fams">
            <attr name="SystemFileSystem.localizingBundle" stringvalue="ancestris.app.Bundle"/>
            <attr name="command" stringvalue="f"/>
            <attr name="position" intvalue="10"/>
            <file name="ancestris-app-FamQuickSearch.instance"/>
        </folder>
        <folder name="Notes">
            <attr name="SystemFileSystem.localizingBundle" stringvalue="ancestris.app.Bundle"/>
            <attr name="command" stringvalue="n"/>
            <attr name="position" intvalue="20"/>
            <file name="ancestris-app-NoteQuickSearch.instance"/>
        </folder>
        <folder name="Sources">
            <attr name="SystemFileSystem.localizingBundle" stringvalue="ancestris.app.Bundle"/>
            <attr name="command" stringvalue="s"/>
            <attr name="position" intvalue="30"/>
            <file name="ancestris-app-SourQuickSearch.instance"/>
        </folder>
        <folder name="Media">
            <attr name="SystemFileSystem.localizingBundle" stringvalue="ancestris.app.Bundle"/>
            <attr name="command" stringvalue="m"/>
            <attr name="position" intvalue="40"/>
            <file name="ancestris-app-ObjeQuickSearch.instance"/>
        </folder>
        <file name="GoToOption"/>
        <file name="GoToSymbol_hidden"/>
        <file name="GoToType_hidden"/>
        <file name="MavenRepositories_hidden"/>
    </folder>
    
    
    <folder name="Services">
        <folder name="AutoupdateType">
            <attr name="position" intvalue="12"/>
            <file name="ancestris_extensions_update_center.instance">
                <attr name="displayName" bundlevalue="ancestris.app.Bundle#Services/AutoupdateType/ancestris_extensions_update_center.instance"/>
                <attr name="enabled" boolvalue="true"/>
                <attr name="instanceCreate" methodvalue="org.netbeans.modules.autoupdate.updateprovider.AutoupdateCatalogFactory.createUpdateProvider"/>
                <attr name="instanceOf" stringvalue="org.netbeans.spi.autoupdate.UpdateProvider"/>
                <attr name="url" stringvalue="http://dl.ancestris.org/ancestris/nbm/trunk/extensions/updates.xml"/>
                <attr name="SystemFileSystem.localizingBundle" stringvalue="ancestris.app.Bundle"/>
            </file>
            <file name="ancestris_update_center.instance">
                <attr name="displayName" bundlevalue="ancestris.app.Bundle#Services/AutoupdateType/ancestris_update_center.instance"/>
                <attr name="enabled" boolvalue="true"/>
                <attr name="instanceCreate" methodvalue="org.netbeans.modules.autoupdate.updateprovider.AutoupdateCatalogFactory.createUpdateProvider"/>
                <attr name="instanceOf" stringvalue="org.netbeans.spi.autoupdate.UpdateProvider"/>
                <attr name="url" stringvalue="http://dl.ancestris.org/ancestris/nbm/trunk/core/updates.xml"/>
                <attr name="SystemFileSystem.localizingBundle" stringvalue="ancestris.app.Bundle"/>
            </file>
        </folder>
        <folder name="Hidden">
            <attr name="position" intvalue="200"/>
            <file name="ancestris-app-ActionOpenDefault.instance">
                <attr name="instanceClass" stringvalue="ancestris.app.ActionOpenDefault"/>
                <attr name="instanceOf" stringvalue="org.netbeans.api.actions.Openable"/>
                <attr name="position" intvalue="100"/>
            </file>
        </folder>
    </folder>

    <folder name="Shortcuts">
        <file name="D-N.shadow">
            <attr name="originalFile" stringvalue="Actions/File/ancestris-app-ActionNew.instance"/>
        </file>
        <file name="D-S.shadow">
            <attr name="originalFile" stringvalue="Actions/System/org-openide-actions-SaveAction.instance"/>
        </file>
        <file name="D-Z.shadow">
            <attr name="originalFile" stringvalue="Actions/Edit/org-openide-actions-UndoAction.instance"/>
        </file>
        <file name="D-Y.shadow">
            <attr name="originalFile" stringvalue="Actions/Edit/org-openide-actions-RedoAction.instance"/>
        </file>
        <file name="D-C.shadow">
            <attr name="originalFile" stringvalue="Actions/Edit/org-openide-actions-CopyAction.instance"/>
        </file>
        <file name="D-X.shadow">
            <attr name="originalFile" stringvalue="Actions/Edit/org-openide-actions-CutAction.instance"/>
        </file>
        <file name="D-V.shadow">
            <attr name="originalFile" stringvalue="Actions/Edit/org-openide-actions-PasteAction.instance"/>
        </file>
        <file name="D-F.shadow">
            <attr name="originalFile" stringvalue="Actions/Edit/org-openide-actions-FindAction.instance"/>
        </file>
        <file name="D-R.shadow">
            <attr name="originalFile" stringvalue="Actions/Edit/org-openide-actions-ReplaceAction.instance"/>
        </file>
        <file name="DELETE.shadow">
            <attr name="originalFile" stringvalue="Actions/Edit/org-openide-actions-DeleteAction.instance"/>
        </file>
        <file name="F1.shadow">
            <attr name="originalFile" stringvalue="Actions/Help/ancestris-app-ActionOnlineHelp.instance"/>
        </file>
        <file name="OS-U.shadow">
            <attr name="originalFile" stringvalue="Actions/Window/org-netbeans-core-windows-actions-UndockWindowAction.instance"/>
        </file>
        <file name="D-T.shadow">
            <attr name="originalFile" stringvalue="Actions/Window/org-netbeans-core-io-ui-IOWindowAction.instance"/>
        </file>
        <file name="D-P.shadow"> <!-- Ctrl+P -->
            <attr name="originalFile" stringvalue="Actions/File/org-netbeans-modules-print-action-PrintAction.instance"/>
        </file>
        <file name="D-4.shadow_hidden"/>
    </folder>
    
    <folder name="Toolbars">
        <!-- attention ce ce fichier contient les toolbars par defaut (voir aussi http://wiki.netbeans.org/DevFaqHideShowToolbar-->
        <file name="Standard.xml" url="Standard.xml"/>
        <folder name="Misc">
            <attr name="position" intvalue="650"/>
            <attr name="displayName" bundlevalue="ancestris.app.Bundle#Toolbars/Misc"/>
        </folder>
        <folder name="Nav">
            <attr name="position" intvalue="805"/>
            <attr name="displayName" bundlevalue="ancestris.app.Bundle#Toolbars/Nav"/>
            <file name="ancestris-app-ActionHistory.shadow">
                <attr name="originalFile" stringvalue="Actions/Edit/ancestris-app-ActionHistory.instance"/>
                <attr name="position" intvalue="100"/>
            </file>
            <file name="ancestris-app-QuickSearch.shadow">
                <attr name="originalFile" stringvalue="Actions/Edit/org-netbeans-modules-quicksearch-QuickSearchAction.instance"/>
                <attr name="position" intvalue="200"/>
            </file>
        </folder>
        <folder name="Help">
            <attr name="position" intvalue="900"/>
            <attr name="displayName" bundlevalue="ancestris.app.Bundle#Toolbars/Help"/>
            <file name="MyOptions.shadow">
                <attr name="originalFile" stringvalue="Actions/Tools/MyOptions.instance"/>
                <attr name="position" intvalue="100"/>
            </file>
            <file name="ancestris-app-ActionAPropos.shadow">
                <attr name="originalFile" stringvalue="Actions/Help/ancestris-app-ActionAPropos.instance"/>
                <attr name="position" intvalue="200"/>
            </file>
            <file name="ancestris-tools-calc-SendAction.shadow">
                <attr name="originalFile" stringvalue="Actions/Help/ancestris-tools-calc-SendAction.instance"/>
                <attr name="position" intvalue="300"/>
            </file>
            <file name="ancestris-app-ActionOnlineHelp.shadow">
                <attr name="originalFile" stringvalue="Actions/Help/ancestris-app-ActionOnlineHelp.instance"/>
                <attr name="position" intvalue="400"/>
            </file>
        </folder>
        <folder name="File">
            <attr name="position" intvalue="100"/>
            <file name="ancestris-app-ActionNew.shadow">
                <attr name="originalFile" stringvalue="Actions/File/ancestris-app-ActionNew.instance"/>
                <attr name="position" intvalue="-100"/>
            </file>
            <file name="ancestris-app-ActionOpenDefault.shadow">
                <attr name="originalFile" stringvalue="Actions/File/ancestris-app-ActionOpenDefault.instance"/>
                <attr name="position" intvalue="-5"/>
            </file>
            <file name="ancestris-app-ActionOpen.shadow">
                <attr name="originalFile" stringvalue="Actions/File/ancestris-app-ActionOpen.instance"/>
                <attr name="position" intvalue="0"/>
            </file>
            <file name="ancestris-app-ActionClose.shadow">
                <attr name="originalFile" stringvalue="Actions/File/ancestris-app-ActionClose.instance"/>
                <attr name="position" intvalue="10"/>
            </file>
            <!--<file name="ancestris-app-ActionSave.shadow">
                <attr name="originalFile" stringvalue="Actions/File/ancestris-app-ActionSave.instance"/>
                <attr name="position" intvalue="20"/>
            </file>-->
            <file name="org-openide-actions-SaveAction.shadow">
                <attr name="originalFile" stringvalue="Actions/System/org-openide-actions-SaveAction.instance"/>
                <attr name="iconBase" stringvalue="ancestris/view/images/Save.png"/>
                <attr name="position" intvalue="100"/>
            </file>
            <file name="org-openide-actions-SaveAllAction.shadow_hidden"/>
        </folder>
    </folder>

    <!-- XML Workspace Layout part -->
    <folder name="Windows2">
        <folder name="Components"/>
        <folder name="Modes">
            <folder name="ancestris-editor"/>
            <folder name="ancestris-nav"/>
            <folder name="ancestris-output"/>
            <folder name="ancestris-properties"/>
            <folder name="ancestris-table"/>            
            <file name="ancestris-editor.wsmode" url="modes/ancestris-editor.wsmode"/>
            <file name="ancestris-nav.wsmode" url="modes/ancestris-nav.wsmode"/>
            <file name="ancestris-output.wsmode" url="modes/ancestris-output.wsmode"/>
            <file name="ancestris-properties.wsmode" url="modes/ancestris-properties.wsmode"/>
            <file name="ancestris-table.wsmode" url="modes/ancestris-table.wsmode"/>
        </folder>
    </folder>
    
    <folder name="OptionsExport">
        <folder name="General"> <!-- options -->
            <attr name="position" intvalue="100"/>
            <attr name="displayName" bundlevalue="ancestris.app.Bundle#OptionsExport/preferences/options"/>
            <file name="General">
                <attr name="position" intvalue="100"/>
                <attr name="include" stringvalue="config/Preferences/ancestris.*|config/Preferences/org.*|config/Services/.*|etc/.*"/>
                <attr name="exclude" stringvalue="ancestris/ancestris.log.*|config/Preferences/ancestris/core/report.*"/>
                <attr name="displayName" bundlevalue="ancestris.app.Bundle#OptionsExport/preferences/general"/>
            </file>
            <file name="ui">
                <attr name="position" intvalue="200"/>
                <attr name="displayName" bundlevalue="ancestris.app.Bundle#OptionsExport/preferences/ui"/>
                <attr name="include" stringvalue="config/Windows2Local/.*"/>
                <attr name="exclude" stringvalue="config/Windows2Local/Modes.*"/>
            </file>
            <file name="Toolbars">
                <attr name="position" intvalue="300"/>
                <attr name="include" stringvalue="config/Toolbars/.*"/>
                <attr name="exclude" stringvalue="config/Toolbars/Progress/.*"/>
                <attr name="displayName" bundlevalue="org.netbeans.core.windows.resources.Bundle#Toolbars.Options.Export.displayName"/>
            </file>
            <file name="Other_hidden"/>
            <file name="Welcome_hidden"/>
        </folder>
        <folder name="preferences"> <!-- settings -->
            <attr name="position" intvalue="200"/>
            <attr name="displayName" bundlevalue="ancestris.app.Bundle#OptionsExport/preferences"/>
            <file name="gedcoms">
                <attr name="displayName" bundlevalue="ancestris.app.Bundle#OptionsExport/preferences/gedcoms"/>
                <attr name="include" stringvalue="config/Preferences/gedcoms/.*"/>
            </file>
        </folder>
        <folder name="templates"> <!-- models -->
            <attr name="position" intvalue="300"/>
            <attr name="displayName" bundlevalue="ancestris.app.Bundle#OptionsExport/templates"/>
            <file name="blueprint">
                <attr name="displayName" bundlevalue="ancestris.app.Bundle#OptionsExport/blueprints"/>
                <attr name="include" stringvalue="ancestris/blueprints/[^/]*/([^/]*)\.html"/>
            </file>
        </folder>
        <folder name="extensions">
            <attr name="position" intvalue="500"/>
            <attr name="displayName" bundlevalue="ancestris.app.Bundle#OptionsExport/extensions"/>
            <file name="modules">
                <attr name="displayName" bundlevalue="ancestris.app.Bundle#OptionsExport/extensions"/>
                <attr name="include" stringvalue="config/Modules/.*|modules/.*"/>
            </file>
        </folder>
        <file name="Templates_hidden"/>
        <file name="Keyring_hidden"/>
        <folder name="Advanced_hidden"/>
    </folder>
</filesystem>
