<?xml version="1.0" encoding="UTF-8"?>
<!DOCTYPE filesystem PUBLIC "-//NetBeans//DTD Filesystem 1.2//EN" "http://www.netbeans.org/dtds/filesystem-1_2.dtd">
<filesystem>
    <folder name="Actions">
        <folder name="Window">
            <file name="ancestris-modules-editors-gedcom-EditAction.instance">
                <attr name="SystemFileSystem.localizingBundle" stringvalue="ancestris.modules.editors.gedcom.Bundle"/>
                <attr name="component" methodvalue="ancestris.modules.editors.gedcom.GedcomTopComponent.getFactory"/>
                <attr name="displayName" bundlevalue="ancestris.modules.editors.gedcom.Bundle#CTL_MENU_EditAction"/>
                <attr name="instanceCreate" methodvalue="ancestris.view.AncestrisTopComponent.openAction"/>
            </file>
        </folder>
    </folder>
    <folder name="Menu">
        <folder name="View">
            <file name="EditAction.shadow">
                <attr name="originalFile" stringvalue="Actions/Window/ancestris-modules-editors-gedcom-EditAction.instance"/>
                <attr name="position" intvalue="-500"/>
            </file>
        </folder>
    </folder>
</filesystem>
